sasrec/__init__.py
sasrec/model.py
sasrec/sampler.py
sasrec/util.py
ezSASRec-1.0.1.dist-info/LICENSE.md
ezSASRec-1.0.1.dist-info/METADATA
ezSASRec-1.0.1.dist-info/WHEEL
ezSASRec-1.0.1.dist-info/top_level.txt
ezSASRec-1.0.1.dist-info/RECORD
