Metadata-Version: 2.1
Name: ezSASRec
Version: 1.0.1
Summary: easy SASRec
Home-page: https://github.com/beomso0/ezSASRec
Author: Beomso0
Author-email: univ3352@gmail.com
License: MIT
Keywords: sasrec,recommendation,sequential
Platform: UNKNOWN
Classifier: Programming Language :: Python :: 3
Requires-Python: >=3.7
License-File: LICENSE.md
Requires-Dist: tensorflow
Requires-Dist: numpy
Requires-Dist: pandas
Requires-Dist: tqdm
